raxopy/__init__.py
raxopy/functions.py
raxopy-1.3.dist-info/METADATA
raxopy-1.3.dist-info/WHEEL
raxopy-1.3.dist-info/top_level.txt
raxopy-1.3.dist-info/RECORD
