Metadata-Version: 2.1
Name: raxopy
Version: 1.3
Summary: Librería creada por un adolescente, para agilizar sobretodo procesos matemáticos.
Home-page: UNKNOWN
Author: raxo1710
Author-email: raxopy@gmail.com
License: UNKNOWN
Platform: UNKNOWN
